tests/__init__.py
tests/torchgan/__init__.py
tests/torchgan/test_layers.py
tests/torchgan/test_losses.py
tests/torchgan/test_metrics.py
tests/torchgan/test_models.py
tests/torchgan/test_trainer.py
torchgan/__init__.py
torchgan/utils.py
torchgan/layers/__init__.py
torchgan/layers/denseblock.py
torchgan/layers/minibatchdiscrimination.py
torchgan/layers/residual.py
torchgan/layers/selfattention.py
torchgan/layers/spectralnorm.py
torchgan/layers/virtualbatchnorm.py
torchgan/logging/__init__.py
torchgan/logging/backends.py
torchgan/logging/logger.py
torchgan/logging/visualize.py
torchgan/losses/__init__.py
torchgan/losses/auxclassifier.py
torchgan/losses/boundaryequilibrium.py
torchgan/losses/draganpenalty.py
torchgan/losses/energybased.py
torchgan/losses/featurematching.py
torchgan/losses/functional.py
torchgan/losses/historical.py
torchgan/losses/leastsquares.py
torchgan/losses/loss.py
torchgan/losses/minimax.py
torchgan/losses/mutualinfo.py
torchgan/losses/wasserstein.py
torchgan/metrics/__init__.py
torchgan/metrics/classifierscore.py
torchgan/metrics/metric.py
torchgan/models/__init__.py
torchgan/models/acgan.py
torchgan/models/autoencoding.py
torchgan/models/conditional.py
torchgan/models/dcgan.py
torchgan/models/infogan.py
torchgan/models/model.py
torchgan/trainer/__init__.py
torchgan/trainer/base_trainer.py
torchgan/trainer/parallel_trainer.py
torchgan/trainer/trainer.py
torchgan-0.1.0.dist-info/LICENSE
torchgan-0.1.0.dist-info/METADATA
torchgan-0.1.0.dist-info/WHEEL
torchgan-0.1.0.dist-info/top_level.txt
torchgan-0.1.0.dist-info/zip-safe
torchgan-0.1.0.dist-info/RECORD
