Metadata-Version: 2.1
Name: torchgan
Version: 0.1.0
Summary: Research Framework for easy and efficient training of GANs based on Pytorch
Home-page: https://github.com/torchgan/torchgan
Author: Avik Pal & Aniket Das
Author-email: avikpal@cse.iitk.ac.in
License: MIT
Keywords: deep learning,pytorch,GAN,AI
Platform: UNKNOWN
Classifier: Environment :: Console
Classifier: Natural Language :: English
Classifier: Development Status :: 4 - Beta
Classifier: Intended Audience :: Developers
Classifier: Topic :: Scientific/Engineering :: Artificial Intelligence
Classifier: Topic :: Scientific/Engineering :: Image Recognition
Classifier: License :: OSI Approved :: MIT License
Classifier: Operating System :: OS Independent
Classifier: Programming Language :: Python :: 3
Classifier: Programming Language :: Python :: 3.6
Classifier: Programming Language :: Python :: 3.7
Classifier: Programming Language :: Python :: 3.8
Requires-Python: >=3.6
Requires-Dist: numpy
Requires-Dist: pillow
Requires-Dist: scipy
Requires-Dist: torch (>=1.2)
Requires-Dist: torchvision (>=0.4)
Requires-Dist: wget
